playgolf_package/__init__.py
playgolf_package/decision_tree.py
playgolf_package/playgolf_data.csv
playgolf_package/playgolf_test.csv
playgolf_package-0.5.dist-info/METADATA
playgolf_package-0.5.dist-info/WHEEL
playgolf_package-0.5.dist-info/top_level.txt
playgolf_package-0.5.dist-info/RECORD
