Metadata-Version: 2.1
Name: playgolf-package
Version: 0.5
Summary: A package for decision tree implementation with datasets included
Home-page: UNKNOWN
License: UNKNOWN
Platform: UNKNOWN
Requires-Dist: pandas
